{
  "main": {
    "id": "0b3a2fb8923b7388",
    "type": "split",
    "children": [
      {
        "id": "6bd813023fe53473",
        "type": "tabs",
        "children": [
          {
            "id": "116a24984d2bee95",
            "type": "leaf",
            "state": {
              "type": "markdown",
              "state": {
                "file": "2月10日-3月2日.md",
                "mode": "source",
                "source": true
              }
            }
          }
        ]
      }
    ],
    "direction": "vertical"
  },
  "left": {
    "id": "0fbb0601c47acb1e",
    "type": "split",
    "children": [
      {
        "id": "68922fe6c6da87d0",
        "type": "tabs",
        "children": [
          {
            "id": "d8d35b9d881b80d1",
            "type": "leaf",
            "state": {
              "type": "file-explorer",
              "state": {
                "sortOrder": "alphabetical"
              }
            }
          },
          {
            "id": "9770adc1093a142b",
            "type": "leaf",
            "state": {
              "type": "search",
              "state": {
                "query": "音乐节",
                "matchingCase": false,
                "explainSearch": false,
                "collapseAll": false,
                "extraContext": false,
                "sortOrder": "alphabetical"
              }
            }
          }
        ]
      }
    ],
    "direction": "horizontal",
    "width": 205.5
  },
  "right": {
    "id": "e82d3653563b026e",
    "type": "split",
    "children": [
      {
        "id": "43ce70f63662d5fd",
        "type": "tabs",
        "children": [
          {
            "id": "0889cda8dd2eed26",
            "type": "leaf",
            "state": {
              "type": "backlink",
              "state": {
                "file": "2月10日-3月2日.md",
                "collapseAll": false,
                "extraContext": false,
                "sortOrder": "alphabetical",
                "showSearch": true,
                "searchQuery": "next",
                "backlinkCollapsed": false,
                "unlinkedCollapsed": true
              }
            }
          },
          {
            "id": "d39b775660bc1d6e",
            "type": "leaf",
            "state": {
              "type": "outline",
              "state": {
                "file": "2月10日-3月2日.md"
              }
            }
          },
          {
            "id": "2a00d507e1d1211a",
            "type": "leaf",
            "state": {
              "type": "calendar",
              "state": {}
            }
          }
        ]
      }
    ],
    "direction": "horizontal",
    "width": 206.5
  },
  "left-ribbon": {
    "hiddenItems": {
      "canvas:新建白板": false,
      "switcher:打开快速切换": false,
      "graph:查看关系图谱": false,
      "templates:插入模板": false,
      "command-palette:打开命令面板": false,
      "markdown-importer:打开 Markdown 格式转换器": false,
      "workspaces:管理工作区布局": false
    }
  },
  "active": "116a24984d2bee95",
  "lastOpenFiles": [
    "1月25日-2月9日.md",
    "8月15日-8月28日.md",
    "4月24日-4月30日周记.md",
    "4月17日-4月23日周记.md",
    "2月10日-3月2日.md",
    "2022复盘.md",
    "pmp.md",
    "12月19日-1月25日.md",
    "6月19日-6月25日周记.md",
    "11月20日-12月18日.md",
    "12月19日-12月18日.md",
    "5月周记2/index.md",
    "5月周记2/稿定设计导出-20220514-180652.jpg",
    "web3/freshman.png",
    "web3/pic1.png",
    "web3/index.md",
    "4月周记1/index.md"
  ]
}